{"classification":{"category":{"name":"Microsoft Azure","normalized_name":"microsoft-azure","subcategories":[{"name":"Storage Services","normalized_name":"storage-services"}]}},"foundation":"Multi-Cloud Platform","items":[{"category":"Microsoft Azure","id":"microsoft-azure--storage-services--azure-blob-storage","name":"Azure Blob Storage","logo":"","subcategory":"Storage Services","website":"https://azure.microsoft.com/services/storage/blobs/","description":"Massively scalable cloud object storage","maturity":"graduated"},{"category":"Microsoft Azure","id":"microsoft-azure--storage-services--azure-managed-disks","name":"Azure Managed Disks","logo":"","subcategory":"Storage Services","website":"https://azure.microsoft.com/services/managed-disks/","description":"Persistent block storage for VMs"},{"category":"Microsoft Azure","id":"microsoft-azure--storage-services--azure-files","name":"Azure Files","logo":"","subcategory":"Storage Services","website":"https://azure.microsoft.com/services/storage/files/","description":"Fully managed file shares"}]}