{"items":[{"category":"IBM Cloud","homepage_url":"https://www.ibm.com/cloud/virtual-servers","id":"ibm-cloud--compute-services--virtual-servers","logo":"","name":"Virtual Servers","subcategory":"Compute Services","website":"https://www.ibm.com/cloud/virtual-servers","description":"Scalable virtual machines on demand"},{"category":"IBM Cloud","homepage_url":"https://www.ibm.com/cloud/functions","id":"ibm-cloud--compute-services--cloud-functions","logo":"","name":"Cloud Functions","subcategory":"Compute Services","website":"https://www.ibm.com/cloud/functions","description":"Serverless compute for event-driven workloads"},{"category":"IBM Cloud","homepage_url":"https://www.ibm.com/cloud/code-engine","id":"ibm-cloud--compute-services--code-engine","logo":"","name":"Code Engine","subcategory":"Compute Services","website":"https://www.ibm.com/cloud/code-engine","description":"Fully managed serverless platform"},{"category":"IBM Cloud","homepage_url":"https://www.ibm.com/cloud/openshift","id":"ibm-cloud--compute-services--openshift-on-ibm-cloud","logo":"","name":"OpenShift on IBM Cloud","subcategory":"Compute Services","website":"https://www.ibm.com/cloud/openshift","description":"Managed container orchestration with Red Hat OpenShift"},{"category":"IBM Cloud","homepage_url":"https://www.ibm.com/cloud/bare-metal","id":"ibm-cloud--compute-services--bare-metal-servers","logo":"","name":"Bare Metal Servers","subcategory":"Compute Services","website":"https://www.ibm.com/cloud/bare-metal","description":"Single-tenant dedicated servers"},{"category":"IBM Cloud","homepage_url":"https://www.ibm.com/cloud/hyper-protect","id":"ibm-cloud--compute-services--hyper-protect-servers","logo":"","name":"Hyper Protect Servers","subcategory":"Compute Services","website":"https://www.ibm.com/cloud/hyper-protect","description":"Ultra-secure dedicated servers"},{"category":"IBM Cloud","homepage_url":"https://www.ibm.com/cloud/power-virtual-servers","id":"ibm-cloud--compute-services--power-virtual-servers","logo":"","name":"Power Virtual Servers","subcategory":"Compute Services","website":"https://www.ibm.com/cloud/power-virtual-servers","description":"POWER processors-based virtual servers"},{"category":"IBM Cloud","homepage_url":"https://www.ibm.com/cloud/satellite","id":"ibm-cloud--compute-services--satellite","logo":"","name":"Satellite","subcategory":"Compute Services","website":"https://www.ibm.com/cloud/satellite","description":"Hybrid and edge computing across on-premises and public clouds"},{"category":"IBM Cloud","homepage_url":"https://www.ibm.com/cloud/object-storage","id":"ibm-cloud--storage-services--cloud-object-storage","logo":"","name":"Cloud Object Storage","subcategory":"Storage Services","website":"https://www.ibm.com/cloud/object-storage","description":"Scalable object storage service"},{"category":"IBM Cloud","homepage_url":"https://www.ibm.com/cloud/block-storage","id":"ibm-cloud--storage-services--block-storage","logo":"","name":"Block Storage","subcategory":"Storage Services","website":"https://www.ibm.com/cloud/block-storage","description":"Persistent block storage volumes"},{"category":"IBM Cloud","homepage_url":"https://www.ibm.com/cloud/file-storage","id":"ibm-cloud--storage-services--file-storage","logo":"","name":"File Storage","subcategory":"Storage Services","website":"https://www.ibm.com/cloud/file-storage","description":"Fully managed NFS file system"},{"category":"IBM Cloud","homepage_url":"https://www.ibm.com/cloud/backup-restore","id":"ibm-cloud--storage-services--backup-restore","logo":"","name":"Backup & Restore","subcategory":"Storage Services","website":"https://www.ibm.com/cloud/backup-restore","description":"Data protection and recovery"},{"category":"IBM Cloud","homepage_url":"https://www.ibm.com/cloud/backup","id":"ibm-cloud--storage-services--cloud-backup","logo":"","name":"Cloud Backup","subcategory":"Storage Services","website":"https://www.ibm.com/cloud/backup","description":"Simple cloud backup service"},{"category":"IBM Cloud","homepage_url":"https://www.ibm.com/cloud/aspera","id":"ibm-cloud--storage-services--aspera-high-speed-transfer","logo":"","name":"Aspera High-Speed Transfer","subcategory":"Storage Services","website":"https://www.ibm.com/cloud/aspera","description":"Fast and reliable data transfer"},{"category":"IBM Cloud","homepage_url":"https://www.ibm.com/cloud/db2","id":"ibm-cloud--database-services--db2","logo":"","name":"Db2","subcategory":"Database Services","website":"https://www.ibm.com/cloud/db2","description":"IBM's relational database"},{"category":"IBM Cloud","homepage_url":"https://www.ibm.com/cloud/db2-warehouse","id":"ibm-cloud--database-services--db2-warehouse","logo":"","name":"Db2 Warehouse","subcategory":"Database Services","website":"https://www.ibm.com/cloud/db2-warehouse","description":"Data warehouse and analytics database"},{"category":"IBM Cloud","homepage_url":"https://www.ibm.com/cloud/cloudant","id":"ibm-cloud--database-services--cloudant","logo":"","name":"Cloudant","subcategory":"Database Services","website":"https://www.ibm.com/cloud/cloudant","description":"Fully managed NoSQL database"},{"category":"IBM Cloud","homepage_url":"https://www.ibm.com/cloud/mongodb","id":"ibm-cloud--database-services--mongodb","logo":"","name":"MongoDB","subcategory":"Database Services","website":"https://www.ibm.com/cloud/mongodb","description":"Managed MongoDB database service"},{"category":"IBM Cloud","homepage_url":"https://www.ibm.com/cloud/postgresql","id":"ibm-cloud--database-services--postgresql","logo":"","name":"PostgreSQL","subcategory":"Database Services","website":"https://www.ibm.com/cloud/postgresql","description":"Managed PostgreSQL database service"},{"category":"IBM Cloud","homepage_url":"https://www.ibm.com/cloud/mysql","id":"ibm-cloud--database-services--mysql","logo":"","name":"MySQL","subcategory":"Database Services","website":"https://www.ibm.com/cloud/mysql","description":"Managed MySQL database service"},{"category":"IBM Cloud","homepage_url":"https://www.ibm.com/cloud/data-warehouse","id":"ibm-cloud--database-services--data-warehouse","logo":"","name":"Data Warehouse","subcategory":"Database Services","website":"https://www.ibm.com/cloud/data-warehouse","description":"Enterprise data warehousing"},{"category":"IBM Cloud","homepage_url":"https://www.ibm.com/cloud/db2-recovery","id":"ibm-cloud--database-services--db2-database-recovery","logo":"","name":"Db2 Database Recovery","subcategory":"Database Services","website":"https://www.ibm.com/cloud/db2-recovery","description":"Disaster recovery for Db2"},{"category":"IBM Cloud","homepage_url":"https://www.ibm.com/cloud/redis","id":"ibm-cloud--database-services--redis","logo":"","name":"Redis","subcategory":"Database Services","website":"https://www.ibm.com/cloud/redis","description":"In-memory data store and cache"},{"category":"IBM Cloud","homepage_url":"https://www.ibm.com/cloud/db2-warehouse","id":"ibm-cloud--analytics-services--db2-warehouse","logo":"","name":"Db2 Warehouse","subcategory":"Analytics Services","website":"https://www.ibm.com/cloud/db2-warehouse","description":"Data warehouse and analytics database"},{"category":"IBM Cloud","homepage_url":"https://www.ibm.com/cloud/datastax","id":"ibm-cloud--analytics-services--datastax","logo":"","name":"Datastax","subcategory":"Analytics Services","website":"https://www.ibm.com/cloud/datastax","description":"Apache Cassandra platform"},{"category":"IBM Cloud","homepage_url":"https://www.ibm.com/cloud/spark","id":"ibm-cloud--analytics-services--apache-spark","logo":"","name":"Apache Spark","subcategory":"Analytics Services","website":"https://www.ibm.com/cloud/spark","description":"Managed Apache Spark service"},{"category":"IBM Cloud","homepage_url":"https://www.ibm.com/cloud/streaming-analytics","id":"ibm-cloud--analytics-services--streaming-analytics","logo":"","name":"Streaming Analytics","subcategory":"Analytics Services","website":"https://www.ibm.com/cloud/streaming-analytics","description":"Real-time stream processing"},{"category":"IBM Cloud","homepage_url":"https://www.ibm.com/cloud/watson-studio","id":"ibm-cloud--analytics-services--watson-studio","logo":"","name":"Watson Studio","subcategory":"Analytics Services","website":"https://www.ibm.com/cloud/watson-studio","description":"Enterprise data science platform"},{"category":"IBM Cloud","homepage_url":"https://www.ibm.com/cloud/planning-analytics","id":"ibm-cloud--analytics-services--planning-analytics","logo":"","name":"Planning Analytics","subcategory":"Analytics Services","website":"https://www.ibm.com/cloud/planning-analytics","description":"Corporate planning and analytics"},{"category":"IBM Cloud","homepage_url":"https://www.ibm.com/cloud/cognos-analytics","id":"ibm-cloud--analytics-services--cognos-analytics","logo":"","name":"Cognos Analytics","subcategory":"Analytics Services","website":"https://www.ibm.com/cloud/cognos-analytics","description":"Business intelligence and analytics"},{"category":"IBM Cloud","homepage_url":"https://www.ibm.com/cloud/watson","id":"ibm-cloud--ai-ml-services--watson-ai","logo":"","name":"Watson AI","subcategory":"AI/ML Services","website":"https://www.ibm.com/cloud/watson","description":"AI services and tools from IBM"},{"category":"IBM Cloud","homepage_url":"https://www.ibm.com/cloud/watson-machine-learning","id":"ibm-cloud--ai-ml-services--watson-machine-learning","logo":"","name":"Watson Machine Learning","subcategory":"AI/ML Services","website":"https://www.ibm.com/cloud/watson-machine-learning","description":"Machine learning platform"},{"category":"IBM Cloud","homepage_url":"https://www.ibm.com/cloud/watson-natural-language-understanding","id":"ibm-cloud--ai-ml-services--watson-natural-language-understanding","logo":"","name":"Watson Natural Language Understanding","subcategory":"AI/ML Services","website":"https://www.ibm.com/cloud/watson-natural-language-understanding","description":"Analyze text and extract insights"},{"category":"IBM Cloud","homepage_url":"https://www.ibm.com/cloud/watson-computer-vision","id":"ibm-cloud--ai-ml-services--watson-computer-vision","logo":"","name":"Watson Computer Vision","subcategory":"AI/ML Services","website":"https://www.ibm.com/cloud/watson-computer-vision","description":"Image and video analysis"},{"category":"IBM Cloud","homepage_url":"https://www.ibm.com/cloud/watson-speech-to-text","id":"ibm-cloud--ai-ml-services--watson-speech-to-text","logo":"","name":"Watson Speech to Text","subcategory":"AI/ML Services","website":"https://www.ibm.com/cloud/watson-speech-to-text","description":"Convert speech to text"},{"category":"IBM Cloud","homepage_url":"https://www.ibm.com/cloud/watson-text-to-speech","id":"ibm-cloud--ai-ml-services--watson-text-to-speech","logo":"","name":"Watson Text to Speech","subcategory":"AI/ML Services","website":"https://www.ibm.com/cloud/watson-text-to-speech","description":"Convert text to speech"},{"category":"IBM Cloud","homepage_url":"https://www.ibm.com/cloud/watson-assistant","id":"ibm-cloud--ai-ml-services--watson-assistant","logo":"","name":"Watson Assistant","subcategory":"AI/ML Services","website":"https://www.ibm.com/cloud/watson-assistant","description":"Build conversational AI"},{"category":"IBM Cloud","homepage_url":"https://www.ibm.com/cloud/watson-knowledge-studio","id":"ibm-cloud--ai-ml-services--watson-knowledge-studio","logo":"","name":"Watson Knowledge Studio","subcategory":"AI/ML Services","website":"https://www.ibm.com/cloud/watson-knowledge-studio","description":"Train custom ML models"},{"category":"IBM Cloud","homepage_url":"https://www.ibm.com/cloud/watson-openscale","id":"ibm-cloud--ai-ml-services--watson-openscale","logo":"","name":"Watson OpenScale","subcategory":"AI/ML Services","website":"https://www.ibm.com/cloud/watson-openscale","description":"Monitor ML model performance"},{"category":"IBM Cloud","homepage_url":"https://www.ibm.com/cloud/vpc","id":"ibm-cloud--networking-content-delivery--vpc","logo":"","name":"VPC","subcategory":"Networking & Content Delivery","website":"https://www.ibm.com/cloud/vpc","description":"Isolated virtual private cloud"},{"category":"IBM Cloud","homepage_url":"https://www.ibm.com/cloud/load-balancer","id":"ibm-cloud--networking-content-delivery--load-balancer","logo":"","name":"Load Balancer","subcategory":"Networking & Content Delivery","website":"https://www.ibm.com/cloud/load-balancer","description":"Load balancing service"},{"category":"IBM Cloud","homepage_url":"https://www.ibm.com/cloud/direct-link","id":"ibm-cloud--networking-content-delivery--direct-link","logo":"","name":"Direct Link","subcategory":"Networking & Content Delivery","website":"https://www.ibm.com/cloud/direct-link","description":"Dedicated network connection"},{"category":"IBM Cloud","homepage_url":"https://www.ibm.com/cloud/transit-gateway","id":"ibm-cloud--networking-content-delivery--transit-gateway","logo":"","name":"Transit Gateway","subcategory":"Networking & Content Delivery","website":"https://www.ibm.com/cloud/transit-gateway","description":"Connect networks across regions"},{"category":"IBM Cloud","homepage_url":"https://www.ibm.com/cloud/cdn","id":"ibm-cloud--networking-content-delivery--cdn","logo":"","name":"CDN","subcategory":"Networking & Content Delivery","website":"https://www.ibm.com/cloud/cdn","description":"Content delivery network"},{"category":"IBM Cloud","homepage_url":"https://www.ibm.com/cloud/internet-services","id":"ibm-cloud--networking-content-delivery--internet-services","logo":"","name":"Internet Services","subcategory":"Networking & Content Delivery","website":"https://www.ibm.com/cloud/internet-services","description":"DDoS, WAF, and DNS services"},{"category":"IBM Cloud","homepage_url":"https://www.ibm.com/cloud/virtual-private-endpoint","id":"ibm-cloud--networking-content-delivery--virtual-private-endpoint","logo":"","name":"Virtual Private Endpoint","subcategory":"Networking & Content Delivery","website":"https://www.ibm.com/cloud/virtual-private-endpoint","description":"Private endpoint connectivity"},{"category":"IBM Cloud","homepage_url":"https://www.ibm.com/cloud/db2-replication","id":"ibm-cloud--data-integration-migration--db2-replication","logo":"","name":"Db2 Replication","subcategory":"Data Integration & Migration","website":"https://www.ibm.com/cloud/db2-replication","description":"Data replication for Db2"},{"category":"IBM Cloud","homepage_url":"https://www.ibm.com/cloud/infosphere","id":"ibm-cloud--data-integration-migration--infosphere-datastax","logo":"","name":"InfoSphere DataStax","subcategory":"Data Integration & Migration","website":"https://www.ibm.com/cloud/infosphere","description":"Enterprise data integration"},{"category":"IBM Cloud","homepage_url":"https://www.ibm.com/cloud/streaming-analytics","id":"ibm-cloud--data-integration-migration--streaming-analytics","logo":"","name":"Streaming Analytics","subcategory":"Data Integration & Migration","website":"https://www.ibm.com/cloud/streaming-analytics","description":"Real-time stream processing"},{"category":"IBM Cloud","homepage_url":"https://www.ibm.com/cloud/cloud-pak-for-data","id":"ibm-cloud--data-integration-migration--cloud-pak-for-data","logo":"","name":"Cloud Pak for Data","subcategory":"Data Integration & Migration","website":"https://www.ibm.com/cloud/cloud-pak-for-data","description":"Unified data platform"},{"category":"IBM Cloud","homepage_url":"https://www.ibm.com/cloud/event-streams","id":"ibm-cloud--data-integration-migration--event-streams","logo":"","name":"Event Streams","subcategory":"Data Integration & Migration","website":"https://www.ibm.com/cloud/event-streams","description":"Managed Apache Kafka"},{"category":"IBM Cloud","homepage_url":"https://www.ibm.com/cloud/mq","id":"ibm-cloud--data-integration-migration--mq","logo":"","name":"MQ","subcategory":"Data Integration & Migration","website":"https://www.ibm.com/cloud/mq","description":"Managed message queuing"},{"category":"IBM Cloud","homepage_url":"https://www.ibm.com/cloud/app-connect","id":"ibm-cloud--data-integration-migration--app-connect","logo":"","name":"App Connect","subcategory":"Data Integration & Migration","website":"https://www.ibm.com/cloud/app-connect","description":"Hybrid integration platform for APIs and integrations"},{"category":"IBM Cloud","homepage_url":"https://www.ibm.com/cloud/api-gateway","id":"ibm-cloud--data-integration-migration--api-gateway","logo":"","name":"API Gateway","subcategory":"Data Integration & Migration","website":"https://www.ibm.com/cloud/api-gateway","description":"Create, manage, and deploy APIs"},{"category":"IBM Cloud","homepage_url":"https://www.ibm.com/cloud/activity-tracker","id":"ibm-cloud--observability-monitoring--activity-tracker","logo":"","name":"Activity Tracker","subcategory":"Observability & Monitoring","website":"https://www.ibm.com/cloud/activity-tracker","description":"Track user and application activity for compliance and auditing"},{"category":"IBM Cloud","homepage_url":"https://www.ibm.com/cloud/logging","id":"ibm-cloud--observability-monitoring--logging","logo":"","name":"Logging","subcategory":"Observability & Monitoring","website":"https://www.ibm.com/cloud/logging","description":"Log collection, search, and analysis service"},{"category":"IBM Cloud","homepage_url":"https://www.ibm.com/cloud/monitoring","id":"ibm-cloud--observability-monitoring--cloud-monitoring","logo":"","name":"Cloud Monitoring","subcategory":"Observability & Monitoring","website":"https://www.ibm.com/cloud/monitoring","description":"Monitor metrics and performance of cloud resources"},{"category":"IBM Cloud","homepage_url":"https://www.ibm.com/cloud/cloud-debugger","id":"ibm-cloud--observability-monitoring--cloud-debugger","logo":"","name":"Cloud Debugger","subcategory":"Observability & Monitoring","website":"https://www.ibm.com/cloud/cloud-debugger","description":"Debug applications in cloud environments"},{"category":"IBM Cloud","homepage_url":"https://www.ibm.com/cloud/instana","id":"ibm-cloud--observability-monitoring--instana","logo":"","name":"Instana","subcategory":"Observability & Monitoring","website":"https://www.ibm.com/cloud/instana","description":"AI-powered observability and monitoring"},{"category":"IBM Cloud","homepage_url":"https://www.ibm.com/cloud/key-protect","id":"ibm-cloud--security-services--key-protect","logo":"","name":"Key Protect","subcategory":"Security Services","website":"https://www.ibm.com/cloud/key-protect","description":"Hardware security module service for key management"},{"category":"IBM Cloud","homepage_url":"https://www.ibm.com/cloud/secrets-manager","id":"ibm-cloud--security-services--secrets-manager","logo":"","name":"Secrets Manager","subcategory":"Security Services","website":"https://www.ibm.com/cloud/secrets-manager","description":"Manage secrets and credentials securely"},{"category":"IBM Cloud","homepage_url":"https://www.ibm.com/cloud/iam","id":"ibm-cloud--security-services--identity-and-access-management","logo":"","name":"Identity and Access Management","subcategory":"Security Services","website":"https://www.ibm.com/cloud/iam","description":"Control user access and permissions"},{"category":"IBM Cloud","homepage_url":"https://www.ibm.com/cloud/app-id","id":"ibm-cloud--security-services--app-id","logo":"","name":"App ID","subcategory":"Security Services","website":"https://www.ibm.com/cloud/app-id","description":"User identity and access management for applications"},{"category":"IBM Cloud","homepage_url":"https://www.ibm.com/cloud/hsm","id":"ibm-cloud--security-services--cloud-hsm","logo":"","name":"Cloud HSM","subcategory":"Security Services","website":"https://www.ibm.com/cloud/hsm","description":"Dedicated hardware security module for key management"},{"category":"IBM Cloud","homepage_url":"https://www.ibm.com/cloud/hyper-protect","id":"ibm-cloud--security-services--hyper-protect-dbaas","logo":"","name":"Hyper Protect DBaaS","subcategory":"Security Services","website":"https://www.ibm.com/cloud/hyper-protect","description":"Database as a service with encryption and isolation"},{"category":"IBM Cloud","homepage_url":"https://www.ibm.com/security/qradar","id":"ibm-cloud--ibm-applications--qradar","logo":"","name":"QRadar","subcategory":"IBM Applications","website":"https://www.ibm.com/security/qradar","description":"Security information and event management (SIEM)"},{"category":"IBM Cloud","homepage_url":"https://www.ibm.com/products/ibm-cloud-pak-for-security","id":"ibm-cloud--ibm-applications--ibm-cloud-pak-for-security","logo":"","name":"IBM Cloud Pak for Security","subcategory":"IBM Applications","website":"https://www.ibm.com/products/ibm-cloud-pak-for-security","description":"Integrated security platform and applications"}]}